<?xml version="1.0" encoding="utf-8"?>
<!DOCTYPE hibernate-mapping PUBLIC "-//Hibernate/Hibernate Mapping DTD 3.0//EN"
"http://www.hibernate.org/dtd/hibernate-mapping-3.0.dtd">
<!-- Mapping file autogenerated by MyEclipse Persistence Tools -->
<hibernate-mapping>
	<class name="cn.zqrc.fts2.pro.vo.Clear" table="t_clear">
		<id name="id" column="Id" type="integer">
			<generator class="native"></generator>
		</id>
		
		<property name="clearPort" type="string"></property>
		<property name="inGoodDate" type="java.sql.Timestamp"></property>
		<property name="transportStyle" type="string"></property>
		<property name="tradeTerm" type="string"></property>
		<property name="tradingNation" type="string"></property>
		<property name="originNation" type="string"></property>
		<property name="wagyBillNum" type="string"></property>
		<property name="taxesDate" type="java.sql.Timestamp"></property>
		<property name="tariff" type="string"></property>
		<property name="valueAdded" type="string"></property>
		<property name="exciseTax" type="string"></property>
		<property name="allTax" type="string"></property>
		<property name="comPortDate" type="java.sql.Timestamp"></property>
		<property name="tariffFile" type="string"></property>
		<property name="valueAddedFile" type="string"></property>
		<property name="exciseTaxFile" type="string"></property>
		<property name="portDate" type="java.sql.Timestamp"></property>
		<property name="inPortNum" type="string"></property>
		<property name="portNum" type="string"></property>
		<property name="inPortDoubleHead" type="string"></property>
		<property name="inPortFile" type="string"></property>
		<property name="clearMoney" type="string"></property>
		<property name="warehouseMoney" type="string"></property>
		<property name="info" type="string"></property>
		<property name="reurnDate" type="java.sql.Timestamp"></property>
		
		
		<!-- 关联项目 -->
		<one-to-one name="project" lazy="false" constrained="true"></one-to-one>
	</class>
</hibernate-mapping>
